ai_risk_sdk/__init__.py
ai_risk_sdk/client.py
ai_risk_sdk/config.py
ai_risk_sdk/context.py
ai_risk_sdk/decorators.py
ai_risk_sdk/dlp.py
ai_risk_sdk/middleware.py
littledata_sdk-0.1.0.dist-info/METADATA
littledata_sdk-0.1.0.dist-info/WHEEL
littledata_sdk-0.1.0.dist-info/licenses/LICENSE
littledata_sdk-0.1.0.dist-info/RECORD
