Metadata-Version: 2.4
Name: littledata-sdk
Version: 0.1.0
Summary: Python SDK for LittleData AI Risk & Governance Platform - Monitor, secure, and govern your AI applications
Project-URL: Homepage, https://littledata.ai
Project-URL: Documentation, https://littledata.ai/docs
Project-URL: Repository, https://github.com/littledata-ai/littledata-sdk
Project-URL: Changelog, https://github.com/littledata-ai/littledata-sdk/blob/main/CHANGELOG.md
Project-URL: Issues, https://github.com/littledata-ai/littledata-sdk/issues
Author-email: LittleData <support@littledata.ai>
Maintainer-email: LittleData <support@littledata.ai>
License: MIT
License-File: LICENSE
Keywords: ai,anthropic,dlp,gemini,governance,llm,monitoring,observability,openai,privacy,risk,security
Classifier: Development Status :: 4 - Beta
Classifier: Intended Audience :: Developers
Classifier: License :: OSI Approved :: MIT License
Classifier: Operating System :: OS Independent
Classifier: Programming Language :: Python :: 3
Classifier: Programming Language :: Python :: 3.10
Classifier: Programming Language :: Python :: 3.11
Classifier: Programming Language :: Python :: 3.12
Classifier: Topic :: Security
Classifier: Topic :: Software Development :: Libraries :: Python Modules
Classifier: Topic :: System :: Monitoring
Classifier: Typing :: Typed
Requires-Python: >=3.10
Requires-Dist: httpx>=0.26.0
Requires-Dist: pydantic>=2.5.0
Provides-Extra: all
Requires-Dist: starlette>=0.27.0; extra == 'all'
Provides-Extra: dev
Requires-Dist: mypy>=1.7.0; extra == 'dev'
Requires-Dist: pytest-asyncio>=0.23.0; extra == 'dev'
Requires-Dist: pytest-httpx>=0.30.0; extra == 'dev'
Requires-Dist: pytest>=7.4.0; extra == 'dev'
Requires-Dist: ruff>=0.1.0; extra == 'dev'
Provides-Extra: middleware
Requires-Dist: starlette>=0.27.0; extra == 'middleware'
